tabbiomed/__init__.py
tabbiomed-0.0.0.dist-info/METADATA
tabbiomed-0.0.0.dist-info/WHEEL
tabbiomed-0.0.0.dist-info/top_level.txt
tabbiomed-0.0.0.dist-info/RECORD
