Metadata-Version: 2.4
Name: tabbiomed
Version: 0.0.0
Summary: TabBioMed
Author-email: David Bonet <davidbonetsole@gmail.com>
Requires-Python: >=3.8
